trackgrab/main.py
trackgrab-0.1.0.dist-info/LICENSE
trackgrab-0.1.0.dist-info/METADATA
trackgrab-0.1.0.dist-info/WHEEL
trackgrab-0.1.0.dist-info/RECORD
