Metadata-Version: 2.1
Name: trackgrab
Version: 0.1.0
Summary: Minimal tool to download your favourite songs from Spotify!
License: MIT
Author: Somraj Saha
Author-email: somraj.mle@gmail.com
Requires-Python: >=3.11,<4.0
Classifier: License :: OSI Approved :: MIT License
Classifier: Programming Language :: Python :: 3
Classifier: Programming Language :: Python :: 3.11
Requires-Dist: click (>=8.1.3,<9.0.0)
Requires-Dist: spotipy (>=2.23.0,<3.0.0)
Requires-Dist: youtube-dl (>=2021.12.17,<2022.0.0)
